Metadata-Version: 1.1
Name: short-chn-yn
Version: 0.0.2
Summary: Short Chinses literal YES or NO recognition by logic
Home-page: https://github.com/foowaa/short-chn-yn/
Author: cltian
Author-email: cl.tian@live.com
License: UNKNOWN
Keywords: Chinese,NLP
Platform: UNKNOWN
Classifier: Programming Language :: Python :: 3.7
Classifier: License :: OSI Approved :: MIT License
Classifier: Operating System :: OS Independent
Classifier: Natural Language :: Chinese (Simplified)
Classifier: Development Status :: 3 - Alpha
Classifier: Topic :: Scientific/Engineering :: Artificial Intelligence
